django_minify_compress_staticfiles/__init__.py
django_minify_compress_staticfiles/conf.py
django_minify_compress_staticfiles/storage.py
django_minify_compress_staticfiles/utils.py
django_minify_compress_staticfiles-1.0.dist-info/licenses/LICENSE
django_minify_compress_staticfiles-1.0.dist-info/METADATA
django_minify_compress_staticfiles-1.0.dist-info/WHEEL
django_minify_compress_staticfiles-1.0.dist-info/top_level.txt
django_minify_compress_staticfiles-1.0.dist-info/RECORD
