Metadata-Version: 2.4
Name: django-minify-compress-staticfiles
Version: 1.0
Summary: Django package for minifying and compressing static files
Home-page: https://github.com/openwisp/django-minify-compress-staticfiles
Author: OpenWISP
Author-email: support@openwisp.io
Keywords: django staticfiles minification compression optimization
Classifier: Development Status :: 5 - Production/Stable
Classifier: Environment :: Web Environment
Classifier: Framework :: Django
Classifier: Framework :: Django :: 4.2
Classifier: Framework :: Django :: 5.0
Classifier: Framework :: Django :: 5.1
Classifier: Framework :: Django :: 5.2
Classifier: Framework :: Django :: 6.0
Classifier: Programming Language :: Python :: 3.10
Classifier: Programming Language :: Python :: 3.11
Classifier: Programming Language :: Python :: 3.12
Classifier: Programming Language :: Python :: 3.13
Classifier: Topic :: Internet :: WWW/HTTP
Classifier: Topic :: Internet :: WWW/HTTP :: Site Management
Classifier: Topic :: Software Development :: Libraries :: Python Modules
Requires-Python: >=3.10
License-File: LICENSE
Requires-Dist: rjsmin<2.0.0,>=1.2.0
Requires-Dist: rcssmin<2.0.0,>=1.1.0
Requires-Dist: brotli<2.0.0,>=1.2.0
Provides-Extra: test
Requires-Dist: openwisp-utils[qa]~=1.2.2; extra == "test"
Dynamic: author
Dynamic: author-email
Dynamic: classifier
Dynamic: description
Dynamic: description-content-type
Dynamic: home-page
Dynamic: keywords
Dynamic: license-file
Dynamic: provides-extra
Dynamic: requires-dist
Dynamic: requires-python
Dynamic: summary
